odoo8_addon_sale_stock_picking_back2draft-8.0.1.0.0.99.dev10-py2.7-nspkg.pth
odoo8_addon_sale_stock_picking_back2draft-8.0.1.0.0.99.dev10.dist-info/DESCRIPTION.rst
odoo8_addon_sale_stock_picking_back2draft-8.0.1.0.0.99.dev10.dist-info/METADATA
odoo8_addon_sale_stock_picking_back2draft-8.0.1.0.0.99.dev10.dist-info/RECORD
odoo8_addon_sale_stock_picking_back2draft-8.0.1.0.0.99.dev10.dist-info/WHEEL
odoo8_addon_sale_stock_picking_back2draft-8.0.1.0.0.99.dev10.dist-info/metadata.json
odoo8_addon_sale_stock_picking_back2draft-8.0.1.0.0.99.dev10.dist-info/namespace_packages.txt
odoo8_addon_sale_stock_picking_back2draft-8.0.1.0.0.99.dev10.dist-info/top_level.txt
odoo_addons/sale_stock_picking_back2draft/README.rst
odoo_addons/sale_stock_picking_back2draft/__init__.py
odoo_addons/sale_stock_picking_back2draft/__openerp__.py
odoo_addons/sale_stock_picking_back2draft/i18n/ca.po
odoo_addons/sale_stock_picking_back2draft/i18n/de.po
odoo_addons/sale_stock_picking_back2draft/i18n/es.po
odoo_addons/sale_stock_picking_back2draft/i18n/es_AR.po
odoo_addons/sale_stock_picking_back2draft/i18n/es_MX.po
odoo_addons/sale_stock_picking_back2draft/i18n/fi.po
odoo_addons/sale_stock_picking_back2draft/i18n/fr.po
odoo_addons/sale_stock_picking_back2draft/i18n/hr.po
odoo_addons/sale_stock_picking_back2draft/i18n/it.po
odoo_addons/sale_stock_picking_back2draft/i18n/pt.po
odoo_addons/sale_stock_picking_back2draft/i18n/pt_BR.po
odoo_addons/sale_stock_picking_back2draft/i18n/sl.po
odoo_addons/sale_stock_picking_back2draft/i18n/tr.po
odoo_addons/sale_stock_picking_back2draft/i18n/tr_TR.po
odoo_addons/sale_stock_picking_back2draft/models/__init__.py
odoo_addons/sale_stock_picking_back2draft/models/stock.py
odoo_addons/sale_stock_picking_back2draft/static/description/icon.png
odoo_addons/sale_stock_picking_back2draft/tests/__init__.py
odoo_addons/sale_stock_picking_back2draft/tests/test_sale.py
